whisper_transcribe/__init__.py
whisper_transcribe/helpers.py
whisper_transcribe/main.py
whisper_transcribe-0.1.1.dist-info/LICENSE
whisper_transcribe-0.1.1.dist-info/METADATA
whisper_transcribe-0.1.1.dist-info/WHEEL
whisper_transcribe-0.1.1.dist-info/RECORD
