Metadata-Version: 2.1
Name: whisper-transcribe
Version: 0.1.1
Summary: Python video transcriber that uses OpenAI's WhisperAI.
License: MIT
Author: Daniel K. Elder
Author-email: elder.dk@gmail.com
Requires-Python: >=3.9,<4.0
Classifier: License :: OSI Approved :: MIT License
Classifier: Programming Language :: Python :: 3
Classifier: Programming Language :: Python :: 3.9
Classifier: Programming Language :: Python :: 3.10
Classifier: Programming Language :: Python :: 3.11
Requires-Dist: openai (>=0.27.2,<0.28.0)
Requires-Dist: tiktoken (>=0.3.2,<0.4.0)
Requires-Dist: yt-dlp (>=2023.3.4,<2024.0.0)
